test_read/__init__.py
test_read/read.py
test_read-2.dist-info/LICENSE
test_read-2.dist-info/METADATA
test_read-2.dist-info/WHEEL
test_read-2.dist-info/top_level.txt
test_read-2.dist-info/RECORD
