Metadata-Version: 2.1
Name: test_read
Version: 2
Summary: test_read
Home-page: UNKNOWN
License: UNKNOWN
Platform: UNKNOWN
License-File: LICENSE
